argenta/__init__.py
argenta/py.typed
argenta/app/__init__.py
argenta/app/defaults.py
argenta/app/models.py
argenta/app/protocols.py
argenta/app/autocompleter/__init__.py
argenta/app/autocompleter/entity.py
argenta/app/dividing_line/__init__.py
argenta/app/dividing_line/models.py
argenta/app/registered_routers/__init__.py
argenta/app/registered_routers/entity.py
argenta/command/__init__.py
argenta/command/exceptions.py
argenta/command/models.py
argenta/command/flag/__init__.py
argenta/command/flag/defaults.py
argenta/command/flag/models.py
argenta/command/flag/flags/__init__.py
argenta/command/flag/flags/models.py
argenta/di/__init__.py
argenta/di/integration.py
argenta/di/providers.py
argenta/metrics/__init__.py
argenta/metrics/main.py
argenta/orchestrator/__init__.py
argenta/orchestrator/entity.py
argenta/orchestrator/argparser/__init__.py
argenta/orchestrator/argparser/entity.py
argenta/orchestrator/argparser/arguments/__init__.py
argenta/orchestrator/argparser/arguments/models.py
argenta/response/__init__.py
argenta/response/entity.py
argenta/response/status.py
argenta/router/__init__.py
argenta/router/defaults.py
argenta/router/entity.py
argenta/router/exceptions.py
argenta/router/command_handler/__init__.py
argenta/router/command_handler/entity.py
argenta-1.1.2.dist-info/METADATA
argenta-1.1.2.dist-info/WHEEL
argenta-1.1.2.dist-info/licenses/LICENSE
argenta-1.1.2.dist-info/RECORD
