Metadata-Version: 2.4
Name: argenta
Version: 1.1.2
Summary: Python library for building modular CLI applications
Author-email: kolo <kolo.is.main@gmail.com>
License: MIT
License-File: LICENSE
Requires-Python: >=3.11
Requires-Dist: art<7.0,>=6.4
Requires-Dist: dishka>=1.7.2
Requires-Dist: pyreadline3>=3.5.4; sys_platform == 'win32'
Requires-Dist: rich<15.0.0,>=14.0.0
